{"cameraMode":{"drawMode":0,"name":"Shaded","section":"Shading Mode"},"sceneLighting":true,"audioPlay":false,"sceneViewState":{"m_AlwaysRefresh":false,"showFog":true,"showSkybox":true,"showFlares":true,"showImageEffects":true,"showParticleSystems":true,"showVisualEffectGraphs":true,"m_FxEnabled":true},"in2DMode":false,"pivot":{"x":-262.4440002441406,"y":169.57958984375,"z":-213.75433349609376},"rotation":{"x":0.06827706098556519,"y":-0.8297100067138672,"z":0.10409657657146454,"w":0.54416823387146},"size":1203.48046875,"orthographic":false}